vfx_fs_util/__init__.py
vfx_fs_util/__main__.py
vfx_fs_util/api.py
vfx_fs_util/compressed_filepath/__init__.py
vfx_fs_util/compressed_filepath/_base.py
vfx_fs_util/compressed_filepath/errors.py
vfx_fs_util/compressed_filepath/iteration.py
vfx_fs_util/compressed_filepath/tokenize.py
vfx_fs_util/compressed_filepath/types.py
vfx_fs_util/config.json
vfx_fs_util/config.py
vfx_fs_util-0.2.6.dist-info/entry_points.txt
vfx_fs_util-0.2.6.dist-info/LICENSE
vfx_fs_util-0.2.6.dist-info/WHEEL
vfx_fs_util-0.2.6.dist-info/METADATA
vfx_fs_util-0.2.6.dist-info/RECORD
