Metadata-Version: 2.1
Name: vfx-fs-util
Version: 0.2.6
Summary: Utility package for working filesystems in the VFX industry.
License: Apache-2.0
Author: John Andrews
Author-email: john.andrews.drum@gmail.com
Requires-Python: >=3.7,<4.0
Classifier: License :: OSI Approved :: Apache Software License
Classifier: Programming Language :: Python :: 3
Classifier: Programming Language :: Python :: 3.10
Classifier: Programming Language :: Python :: 3.7
Classifier: Programming Language :: Python :: 3.8
Classifier: Programming Language :: Python :: 3.9
Requires-Dist: Lucidity (>=1.6.0,<2.0.0)
Requires-Dist: scandir (>=1.10.0,<2.0.0)
Requires-Dist: typer[all] (>=0.6.1,<0.7.0)
